pytdutils/__init__.py
pytdutils/level.py
pytdutils-1.1.84.dist-info/METADATA
pytdutils-1.1.84.dist-info/WHEEL
pytdutils-1.1.84.dist-info/licenses/LICENSE
pytdutils-1.1.84.dist-info/RECORD
