Metadata-Version: 2.3
Name: pytdutils
Version: 1.1.84
Summary: Interface for tride dash levels
Classifier: License :: OSI Approved :: MIT License
Classifier: Operating System :: OS Independent
Classifier: Programming Language :: Python :: 3
Requires-Python: >=3.8
